KPU_Chip/__init__.py
kpu_chip-0.1.3.dist-info/METADATA
kpu_chip-0.1.3.dist-info/WHEEL
kpu_chip-0.1.3.dist-info/top_level.txt
kpu_chip-0.1.3.dist-info/RECORD
